.clang-format
.gitignore
.pre-commit-config.yaml
.travis.yml
CONTRIBUTORS
LICENSE
MANIFEST.in
Makefile
README.md
pyproject.toml
setup.cfg
.github/workflows/pypi_release.yaml
.github/workflows/python-app.yml
.github/workflows/website.yml
doc/Makefile
doc/source/api.rst
doc/source/conf.py
doc/source/index.rst
doc/source/notebooks
notebooks/fanci_tutorial.ipynb
notebooks/pyci_tutorial.ipynb
pyci/__init__.py
pyci/_pyci.so
pyci/cost_ci.py
pyci/excitation_ci.py
pyci/gkci.py
pyci/seniority_ci.py
pyci/utility.py
pyci/fanci/__init__.py
pyci/fanci/ap1rog.py
pyci/fanci/apig.py
pyci/fanci/detratio.py
pyci/fanci/fanci.py
pyci/fanci/pccds.py
pyci/fanci/test/__init__.py
pyci/fanci/test/derivcheck.py
pyci/fanci/test/test_ap1rog.py
pyci/fanci/test/test_apig.py
pyci/fanci/test/test_detratio.py
pyci/fanci/test/test_objective_fanci.py
pyci/fanci/test/test_pccds.py
pyci/fanci/test/data/be_ccpvdz.fcidump
pyci/fanci/test/data/h2_hf_631gdp.fcidump
pyci/fanci/test/data/h2_hf_sto6g.fcidump
pyci/fanci/test/data/he_ccpvqz.fcidump
pyci/fanci/test/data/li2_631g.fcidump
pyci/fanci/test/data/li2_ccpvdz.fcidump
pyci/fanci/test/data/lih_631g.fcidump
pyci/fanci/test/data/lih_hf_sto6g.fcidump
pyci/include/SpookyV2.h
pyci/include/pyci.h
pyci/include/sort_with_arg.h
pyci/rdm/__init__.py
pyci/rdm/algorithms.py
pyci/rdm/conditions.py
pyci/rdm/constraints.py
pyci/rdm/tools.py
pyci/src/SpookyV2.cpp
pyci/src/ap1rog.cpp
pyci/src/apig.cpp
pyci/src/binding.cpp
pyci/src/common.cpp
pyci/src/dociwfn.cpp
pyci/src/enpt2.cpp
pyci/src/fanci.cpp
pyci/src/fullciwfn.cpp
pyci/src/genciwfn.cpp
pyci/src/hci.cpp
pyci/src/onespinwfn.cpp
pyci/src/overlap.cpp
pyci/src/rdm.cpp
pyci/src/sparseop.cpp
pyci/src/squantop.cpp
pyci/src/twospinwfn.cpp
pyci/src/wfn.cpp
pyci/test/__init__.py
pyci/test/test_hamiltonian.py
pyci/test/test_odometer.py
pyci/test/test_routines.py
pyci/test/test_wavefunction.py
pyci/test/data/be_ccpvdz.fcidump
pyci/test/data/be_ccpvdz_spinres.npz
pyci/test/data/h2_631gdp.fcidump
pyci/test/data/h2_sto3g.fcidump
qc_PyCI.egg-info/PKG-INFO
qc_PyCI.egg-info/SOURCES.txt
qc_PyCI.egg-info/dependency_links.txt
qc_PyCI.egg-info/requires.txt
qc_PyCI.egg-info/top_level.txt
