Metadata-Version: 2.1
Name: qc-PyCI
Version: 0.6.1a5
Summary: PyCI: A flexible quantum chemistry CI library for Python 3.
Author-email: QC-Devs Community <qcdevs@gmail.com>
License:                     GNU GENERAL PUBLIC LICENSE
Project-URL: Homepage, https://github.com/theochem/pyci
Project-URL: Source, https://github.com/theochem/pyci
Project-URL: Issues, https://github.com/theochem/pyci/issues
Project-URL: Documentation, https://pyci.qcdevs.org/
Keywords: quantum chemistry,configuration interaction,theoretical chemistry
Classifier: Development Status :: 5 - Production/Stable
Classifier: Intended Audience :: Science/Research
Classifier: Intended Audience :: Developers
Classifier: Topic :: Scientific/Engineering :: Chemistry
Classifier: Topic :: Scientific/Engineering :: Physics
Classifier: Topic :: Scientific/Engineering :: Mathematics
Classifier: License :: OSI Approved :: GNU General Public License v3 (GPLv3)
Classifier: Programming Language :: Python :: 3.9
Classifier: Programming Language :: Python :: 3.10
Classifier: Programming Language :: Python :: 3.11
Classifier: Programming Language :: Python :: 3.12
Classifier: Programming Language :: Python :: 3
Classifier: Programming Language :: C++
Requires-Python: >=3.9
License-File: LICENSE
Requires-Dist: numpy>=1.13
Requires-Dist: scipy>=1.0
Provides-Extra: test
Requires-Dist: pytest>=6.0; extra == "test"
Requires-Dist: pycodestyle; extra == "test"
Requires-Dist: pydocstyle; extra == "test"
Provides-Extra: doc
Requires-Dist: sphinx; extra == "doc"
Requires-Dist: nbsphinx; extra == "doc"
Requires-Dist: sphinx_rtd_theme; extra == "doc"
